kumar_missingdata/MissingData.py
kumar_missingdata-1.0.3.dist-info/LICENSE.txt
kumar_missingdata-1.0.3.dist-info/METADATA
kumar_missingdata-1.0.3.dist-info/WHEEL
kumar_missingdata-1.0.3.dist-info/entry_points.txt
kumar_missingdata-1.0.3.dist-info/top_level.txt
kumar_missingdata-1.0.3.dist-info/RECORD
