Metadata-Version: 2.1
Name: kumar-missingdata
Version: 1.0.3
Summary: Technique for handling missing data.
Home-page: UNKNOWN
Author: kumar
Author-email: 
License: MIT
Platform: UNKNOWN
Classifier: License :: OSI Approved :: MIT License
Classifier: Programming Language :: Python :: 3
Classifier: Programming Language :: Python :: 3.7
Classifier: Programming Language :: Python :: 2.7
Requires-Dist: pandas
Requires-Dist: numpy
